{
	"\n김동연 \"10·29 참사에 윤 대통령이 진정성 갖고 사과해야\"\n": "http://www.yna.co.kr/view/AKR20221125137700061?section=disaster/news",
	"\n조국 재판 내달 2일 마무리…이르면 연내 1심 선고\n": "http://www.yna.co.kr/view/AKR20221125132400004?section=society/all",
	"\n질병청 \"BA.5 유행시기 사망·위중증 비율, 델타 때의 21분의 1\"\n": "http://www.yna.co.kr/view/AKR20221125132300530?section=coronavirus/news",
	"\n예열하는 황희찬·몸 풀린 이강인, 가나전 '비장의 무기' 되나\n": "http://www.yna.co.kr/view/AKR20221127006500007?section=worldcup-2022/news",
	"\n유동성 위기 은행으로 번지나…은행채·금리 묶인채 대출만 펑펑\n": "http://www.yna.co.kr/view/AKR20221126038600002?section=economy/all",
	"\n중부 낮 최고 10도 내외 추위…내륙 일부 한파특보\n": "http://www.yna.co.kr/view/AKR20221127004100034?section=society/all",
	"\n초유의 장군 강등…전익수 공군 법무실장, 준장서 대령으로\n": "http://www.yna.co.kr/view/AKR20221125151751504?section=news",
	"\n'메시 결승골' 아르헨티나, 멕시코 2-0 완파하고 '기사회생'\n": "http://www.yna.co.kr/view/AKR20221127004600007?section=worldcup-2022/news",
	"\n'가나전 D-2' 준비 박차 가하는 벤투호…황희찬도 복귀 임박?\n": "http://www.yna.co.kr/view/AKR20221126042300007?section=worldcup-2022/news",
	"\n김정은, 공개행사에 또 둘째딸 동행…\"핵전쟁억제력 강화\"\n": "http://www.yna.co.kr/view/AKR20221127005751504?section=politics/all",
	"\n與, 터질듯 말듯 아슬아슬…'尹관저 회동'으로 봉합되나\n": "http://www.yna.co.kr/view/AKR20221126035300001?section=politics/all",
	"\n이재명, 사법리스크 정면돌파하나…내달초 '100일 메시지' 주목\n": "http://www.yna.co.kr/view/AKR20221126038900001?section=politics/all",
	"\n\"국민이 낸 보험료를 눈먼 돈으로 인식\"…건보재정 누수 심각\n": "http://www.yna.co.kr/view/AKR20221125067200501?section=society/all",
	"\n정부, '11억원 문턱' 민주 종부세안 거부…중과 폐지 고수\n": "http://www.yna.co.kr/view/AKR20221126021600002?section=economy/all",
	"\n예산국회 막판까지 파열음…여야 '윤석열·이재명표' 예산 공방\n": "http://www.yna.co.kr/view/AKR20221125136100001?section=politics/all",
	"\n김정은, ICBM 공로자들과 기념사진…둘째딸 또 동행\n": "http://www.yna.co.kr/view/AKR20221127005700504?section=politics/all",
	"\n입시 부담에 잠 못 자는 고3들…절반은 하루 6시간도 못 자\n": "http://www.yna.co.kr/view/AKR20221125115000530?section=society/all",
	"\n여가부 폐지·'기관장 알박기 금지' 논의한다지만…입장차 확연\n": "http://www.yna.co.kr/view/AKR20221126025400001?section=politics/all",
	"\n은행 이자 폭리 막는다…예대금리차 내달부터 매월 공시\n": "http://www.yna.co.kr/view/AKR20221126018600002?section=economy/all",
	"\n 北김정은 \"국방력 불가역적으로…핵전쟁억제력 비상히 강화\"\n": "http://www.yna.co.kr/view/AKR20221127005000504?section=nk/news/all",
	"\n'5對13'…대만 지방선거 집권 민진당 참패·국민당 승리\n": "http://www.yna.co.kr/view/AKR20221126040052083?section=international/all",
	"\n항만 물류 80% 급감…정부 \"업무개시명령 발동 준비 마쳐\"\n": "http://www.yna.co.kr/view/AKR20221126023751003?section=economy/all",
	"\n대만 지방선거, 집권 민진당 참패·국민당 승리\n": "http://www.yna.co.kr/view/AKR20221126040051083?section=international/all",
	"\n폴란드, 사우디 중동 바람 잠재웠다…레반도프스키 드디어 첫 골\n": "http://www.yna.co.kr/view/AKR20221127000300007?section=worldcup-2022/news"
}