{
	"\n추경호 \"상생임대인 양도세 비과세 2년 거주요건 완전 면제\"\n": "http://www.yna.co.kr/view/AKR20220621021251002?section=economy/all",
	"\n교총 새 회장에 정성국 부산 해강초 교사…첫 초등교사 회장\n": "http://www.yna.co.kr/view/AKR20220621018100530?section=society/all",
	"\n치솟는 기름값에 차 두고 지하철로…\"러시아워 지나도 붐벼\"\n": "http://www.yna.co.kr/view/AKR20220620140700004?section=economy/all",
	"\n내 나이 100살, 꿈 아니다…'백세인' 9가지 필수조건\n": "http://www.yna.co.kr/view/AKR20220620129200017?section=society/all",
	"\n與, 서해 피격 진상조사TF 첫 회의…오후엔 외교 정책의총\n": "http://www.yna.co.kr/view/AKR20220620147800001?section=politics/all",
	"\n국내 독자 개발 '누리호', 오늘 다시 우주로 향한다\n": "http://www.yna.co.kr/view/AKR20220620138900017?section=industry/all",
	"\n 추경호 \"상생임대인 양도세 비과세 2년 거주요건 완전 면제\"\n": "http://www.yna.co.kr/view/AKR20220621021200002?section=economy/all",
	"\n행안부 '경찰통제안' 오늘 발표…경찰국 신설 등 추진\n": "http://www.yna.co.kr/view/AKR20220620138800530?section=society/all",
	"\n법무부, 오늘 검찰인사위원회…이르면 오후 검사장 인사\n": "http://www.yna.co.kr/view/AKR20220620133100004?section=society/all",
	"\n[한은 물가점검] \"올해 물가 4.7% 넘어설 수도…하반기 오름세 더 확대\"\n": "http://www.yna.co.kr/view/AKR20220620148600002?section=economy/all",
	"\n尹대통령, 초급간부·부사관 처우개선 당부…활동비 인상키로\n": "http://www.yna.co.kr/view/AKR20220621015700504?section=politics/all",
	"\n러 가스 공급 축소에 독·오스트리아·네덜란드 석탄발전 '유턴'\n": "http://www.yna.co.kr/view/AKR20220620023851009?section=international/all",
	"\n전국 무더위…낮 최고 35도까지 올라\n": "http://www.yna.co.kr/view/AKR20220621004800034?section=society/all",
	"\n'부지런해야 성공한다'…습관형성 위한 자기관리 앱 인기\n": "http://www.yna.co.kr/view/AKR20220620109100003?section=economy/all",
	"\n뉴욕증시, 하락장 초기단계?…WSJ \"통화정책 방향 틀어야 바닥\"\n": "http://www.yna.co.kr/view/AKR20220621010400072?section=economy/all",
	"\n제네시스 SUV 이달 누적판매량 20만대 돌파…출시 후 2년반만\n": "http://www.yna.co.kr/view/AKR20220620142600003?section=industry/all",
	"\n민주, 최강욱에 '6개월 당원 자격정지' 중징계…본인은 부인\n": "http://www.yna.co.kr/view/AKR20220620153651001?section=politics/all",
	"\n일터 내몰리는 노인들…노인소득 절반 이상은 일해서 버는 소득\n": "http://www.yna.co.kr/view/AKR20220620141900530?section=economy/all",
	"\n김여사 '첫 연설' 광폭행보…천공은 \"영부인 바빠져야\" 영상\n": "http://www.yna.co.kr/view/AKR20220620061251001?section=politics/all",
	"\n코레일·LH 경영평가 낙제점…'재무악화' 한전 임원 성과급 반납\n": "http://www.yna.co.kr/view/AKR20220620098252002?section=economy/all",
	"\n이준석 \"윤리위 참석 의사 밝혀…별다른 걱정은 안 해\"\n": "http://www.yna.co.kr/view/AKR20220620115551001?section=politics/all",
	"\n황선우, 세계선수권 자유형 200ｍ 은메달…박태환 넘어 최고성적\n": "http://www.yna.co.kr/view/AKR20220621001351007?section=sports/all",
	"\nSNS이용률 1위는 밀레니얼 83.5%…헤비유저 비율 Z세대 최다\n": "http://www.yna.co.kr/view/AKR20220620127200017?section=industry/all",
	"\n원자재가 상승에 전력-에너지기업 매출액 대비 원재료 비중↑ 수익↓\n": "http://www.yna.co.kr/view/AKR20220620123700003?section=economy/all",
	"\n요금 못 올리고 적자는 눈덩이 '위기의 한전'…자구책도 역부족\n": "http://www.yna.co.kr/view/AKR20220620139800003?section=economy/all",
	"\n[유럽증시] 글로벌 경기침체 불안 속 1% 안팎 반등\n": "http://www.yna.co.kr/view/AKR20220621003100109?section=economy/all",
	"\n발트해 제2화약고 되나…러, 리투아니아 화물 제한에 대응경고\n": "http://www.yna.co.kr/view/AKR20220620153551080?section=international/all",
	"\n'폭풍전야' 與…'이준석 징계 논의' 임박에 당권구도 중대기로\n": "http://www.yna.co.kr/view/AKR20220620068951001?section=politics/all",
	"\n발사예정 전야, 누리호 준비 정상…기상여건도 만족\n": "http://www.yna.co.kr/view/AKR20220620152200017?section=industry/all"
}