{
	"\n\"집주인 대신 갚아주고 못받은 전세보증금, 지난해 3천500억\"\n": "http://www.yna.co.kr/view/AKR20220919145900001?section=politics/all",
	"\n신당역 '스토킹 살해범' 31세 전주환 만장일치 신상공개\n": "http://www.yna.co.kr/view/AKR20220919065753004?section=society/all",
	"\n국회, 이틀째 대정부질문…북핵·대북정책 등 격돌 예상\n": "http://www.yna.co.kr/view/AKR20220919144800001?section=politics/all",
	"\n강풍에 골프장 철탑도 '쿵'…난마돌 스쳐 간 영남권 적잖은 상흔\n": "http://www.yna.co.kr/view/AKR20220919057652057?section=disaster/news",
	"\n폭염특보 풀린 지 이틀 됐는데…서리 걱정할 정도로 기온 '뚝'\n": "http://www.yna.co.kr/view/AKR20220920017600530?section=disaster/news",
	"\n10년물 미 국채금리, 11년만에 첫 3.5% 돌파…경기침체 우려↑\n": "http://www.yna.co.kr/view/AKR20220920000300072?section=economy/all",
	"\n멕시코서 규모 7.6 강진…주민 사망·건물파손 피해 속출\n": "http://www.yna.co.kr/view/AKR20220920003553091?section=international/all",
	"\n경찰청장 \"경검 스토킹 대응 협의체 신설…사건 전수조사\"\n": "http://www.yna.co.kr/view/AKR20220919077500004?section=society/all",
	"\n서울대, '개 복제 전문가' 이병천 수의대 교수 파면 의결\n": "http://www.yna.co.kr/view/AKR20220919161100004?section=society/all",
	"\n韓日외교장관, 뉴욕서 회담…\"강제징용 해법 심도있게 논의\"\n": "http://www.yna.co.kr/view/AKR20220920007352072?section=international/all",
	"\n국가재건 앞둔 우크라, 교과서에 '한강의 기적' 싣는다\n": "http://www.yna.co.kr/view/AKR20220919159900108?section=international/all",
	"\n신재생 발전설비 비중 20% 첫 돌파…태양광은 15% 상회\n": "http://www.yna.co.kr/view/AKR20220919154800003?section=economy/all",
	"\n 韓日외교장관 회담 종료…박진 \"관계개선 위해 진정성갖고 노력\"\n": "http://www.yna.co.kr/view/AKR20220920007351072?section=international/all",
	"\n병무청장 \"BTS 계기로 보충역제도 축소 검토…추가 맞지않아\"\n": "http://www.yna.co.kr/view/AKR20220919128400504?section=politics/all",
	"\n尹, 뉴욕서 2박3일 다자외교…내일 새벽 유엔총회 연설\n": "http://www.yna.co.kr/view/AKR20220919153800001?section=politics/all",
	"\n[르포]'굿바이 여왕' 웨스트민스터 사원 앞 취재구역서 본 마지막 길\n": "http://www.yna.co.kr/view/AKR20220919158051085?section=international/all",
	"\n韓日외교장관, 뉴욕서 회담…정상회담 앞두고 현안조율 차원인듯\n": "http://www.yna.co.kr/view/AKR20220920004600072?section=international/all",
	"\n'이준석 제명' 정진석 문자노출 논란…유상범, 윤리위원 사퇴\n": "http://www.yna.co.kr/view/AKR20220919081152001?section=politics/all",
	"\n전국 구름 많고 기온 큰 폭으로 떨어져…낮 최고 25도\n": "http://www.yna.co.kr/view/AKR20220920006100034?section=disaster/news",
	"\n바이든 '팬데믹 끝' 발언 논란…백악관 \"비상사태해제 계획없다\"\n": "http://www.yna.co.kr/view/AKR20220920004251071?section=international/all",
	"\n주호영 신임 원내대표, 첫 회의 주재…정무수석 예방도\n": "http://www.yna.co.kr/view/AKR20220919154600001?section=politics/all",
	"\n尹, 英여왕 조문록 작성…\"여왕과 동시대 공유해 영광이었다\"\n": "http://www.yna.co.kr/view/AKR20220919159400001?section=politics/all",
	"\n어제 오후 9시 4만5974명 확진, 2주전보다 5만여명↓…10주만에 최저\n": "http://www.yna.co.kr/view/AKR20220919157400530?section=coronavirus/news",
	"\n 韓日외교장관, 뉴욕서 회담…강제징용 해법 등 현안 조율할 듯\n": "http://www.yna.co.kr/view/AKR20220920004500072?section=international/all",
	"\n'70년 군주' 엘리자베스 英여왕 세계와 영국에 작별 고하고 영면\n": "http://www.yna.co.kr/view/AKR20220919152052082?section=international/all"
}